<?xml version="1.0" encoding="UTF-8"?> 
<!DOCTYPE  tiles-definitions PUBLIC 
    "-//Aapche Software Foundation//DTD Tiles Configuration 2.0//EN" 
    "http://tiles.apache.org/dtds/tiles-config_2_0.dtd"> 

<tiles-definitions> 
     <definition name="main" template="/WEB-INF/views/template/template.jsp"> 
        <put-attribute name="header" value="/WEB-INF/views/template/header.jsp" /> 
        <put-attribute name="footer" value="/WEB-INF/views/template/footer.jsp" /> 
    </definition> 
<definition name="/home" extends="main"> 
        <put-attribute name="title" value="기본페이지" ></put-attribute> 
        <put-attribute name="body" value="/WEB-INF/views/home.jsp" /> 
    </definition>   
    <definition name="/team/create" extends="main"> 
        <put-attribute name="title" value="team 생성" ></put-attribute> 
        <put-attribute name="body" value="/WEB-INF/views/team/createForm.jsp" /> 
    </definition>   
    <definition name="/team/update" extends="main"> 
        <put-attribute name="title" value="team 수정" ></put-attribute> 
        <put-attribute name="body" value="/WEB-INF/views/team/updateForm.jsp" /> 
    </definition>  
    <definition name="/team/delete" extends="main"> 
        <put-attribute name="title" value="team 삭제" ></put-attribute> 
        <put-attribute name="body" value="/WEB-INF/views/team/deleteForm.jsp" /> 
    </definition>  
    <definition name="/team/reply" extends="main"> 
        <put-attribute name="title" value="team 답변" ></put-attribute> 
        <put-attribute name="body" value="/WEB-INF/views/team/replyForm.jsp" /> 
    </definition>  
    <definition name="/team/read" extends="main"> 
        <put-attribute name="title" value="team 조회" ></put-attribute> 
        <put-attribute name="body" value="/WEB-INF/views/team/read.jsp" /> 
    </definition>  
    <definition name="/team/list" extends="main"> 
        <put-attribute name="title" value="team 목록" ></put-attribute> 
        <put-attribute name="body" value="/WEB-INF/views/team/list.jsp" /> 
    </definition>  
   
           
     
</tiles-definitions>  
